fivaldi/__init__.py
fivaldi/client.py
fivaldi/api/__init__.py
fivaldi/api/auth.py
fivaldi/api/endpoint.py
fivaldi_api_client-0.0.2.dist-info/METADATA
fivaldi_api_client-0.0.2.dist-info/WHEEL
fivaldi_api_client-0.0.2.dist-info/top_level.txt
fivaldi_api_client-0.0.2.dist-info/RECORD
